[
  {
    "name": "ГИБДД | Права и Законы",
    "link": "https://t.me/joinchat/ISyRrvSptAwwODUy",
    "category": "Право",
    "subs": 281740,
    "avg_views_post": 38288,
    "err": 14.0,
    "migr_sub7d": -1965,
    "migr_sub30d": -9552,
    "lifetime": "1 год 10 месяцев"
  },
  {
    "name": "Gulagu.net ГУЛАГу-НЕТ! 🕊",
    "link": "https://t.me/NetGulagu",
    "category": "Право",
    "subs": 148036,
    "avg_views_post": 30159,
    "err": 21.0,
    "migr_sub7d": -476,
    "migr_sub30d": -2105,
    "lifetime": "5 лет 4 месяца"
  },
  {
    "name": "Заметки юриста",
    "link": "https://t.me/joinchat/iMngXUqx-YhkYTIy",
    "category": "Право",
    "subs": 142820,
    "avg_views_post": 26186,
    "err": 19.0,
    "migr_sub7d": -476,
    "migr_sub30d": -654,
    "lifetime": "4 года 4 месяца"
  },
  {
    "name": "Без долгов с юристом Катряевой",
    "link": "https://t.me/joinchat/P_znm2YkmpoyMDhi",
    "category": "Право",
    "subs": 142072,
    "avg_views_post": 13578,
    "err": 10.0,
    "migr_sub7d": 2466,
    "migr_sub30d": 5327,
    "lifetime": "4 года 24 дня"
  },
  {
    "name": "Родители | Пособия и Льготы РФ",
    "link": "https://t.me/joinchat/nk0yA5IYA5MwOTky",
    "category": "Право",
    "subs": 142015,
    "avg_views_post": 19980,
    "err": 15.0,
    "migr_sub7d": -909,
    "migr_sub30d": -4538,
    "lifetime": "2 года 5 месяцев"
  },
  {
    "name": "ОВД-Инфо",
    "link": "https://t.me/ovdinfo",
    "category": "Право",
    "subs": 139743,
    "avg_views_post": 11257,
    "err": 9.0,
    "migr_sub7d": -397,
    "migr_sub30d": -1319,
    "lifetime": "8 лет 2 месяца"
  },
  {
    "name": "Правовой уголок офицера",
    "link": "https://t.me/voenpravoru",
    "category": "Право",
    "subs": 135846,
    "avg_views_post": 43964,
    "err": 33.0,
    "migr_sub7d": 3337,
    "migr_sub30d": 8293,
    "lifetime": "4 года 14 дней"
  },
  {
    "name": "Правовой вестник СВО",
    "link": "https://t.me/pv_svo",
    "category": "Право",
    "subs": 134389,
    "avg_views_post": 51524,
    "err": 39.0,
    "migr_sub7d": 1560,
    "migr_sub30d": 8460,
    "lifetime": "1 год 6 месяцев"
  },
  {
    "name": "ГИБДД РФ • Законы",
    "link": "https://t.me/joinchat/mTem61BODbA3OWIy",
    "category": "Право",
    "subs": 121915,
    "avg_views_post": 39513,
    "err": 33.0,
    "migr_sub7d": -638,
    "migr_sub30d": -1083,
    "lifetime": "2 года 2 месяца"
  },
  {
    "name": "Юридические Тонкости",
    "link": "https://t.me/sivakovairina",
    "category": "Право",
    "subs": 109325,
    "avg_views_post": 19033,
    "err": 18.0,
    "migr_sub7d": 182,
    "migr_sub30d": 1071,
    "lifetime": "2 года 9 месяцев"
  },
  {
    "name": "Юридическое мнение",
    "link": "https://t.me/joinchat/1p2fC48xtllhY2Qy",
    "category": "Право",
    "subs": 107590,
    "avg_views_post": 17636,
    "err": 17.0,
    "migr_sub7d": -1187,
    "migr_sub30d": -6751,
    "lifetime": "1 год 10 месяцев"
  },
  {
    "name": "МПЦ",
    "link": "https://t.me/mpcrf",
    "category": "Право",
    "subs": 104928,
    "avg_views_post": 67716,
    "err": 65.0,
    "migr_sub7d": 107,
    "migr_sub30d": 2013,
    "lifetime": "5 лет 1 месяц"
  },
  {
    "name": "МЕНТ В ЗАКОНЕ",
    "link": "https://t.me/joinchat/tVLHyU45GNZiNmMy",
    "category": "Право",
    "subs": 89830,
    "avg_views_post": 16309,
    "err": 19.0,
    "migr_sub7d": -627,
    "migr_sub30d": 9221,
    "lifetime": "4 года 7 месяцев"
  },
  {
    "name": "Адвокатское чтиво",
    "link": "https://t.me/joinchat/Ggu_Lvm-rPY4N2Qy",
    "category": "Право",
    "subs": 82628,
    "avg_views_post": 11825,
    "err": 15.0,
    "migr_sub7d": -316,
    "migr_sub30d": -1583,
    "lifetime": "1 год 6 месяцев"
  },
  {
    "name": "ГосУслуги в Telegram",
    "link": "https://t.me/joinchat/uttSZPUqQYwyNTQy",
    "category": "Право",
    "subs": 81621,
    "avg_views_post": 7669,
    "err": 10.0,
    "migr_sub7d": -412,
    "migr_sub30d": -1956,
    "lifetime": "2 года 1 месяц"
  },
  {
    "name": "Бывший опер👮 (полиция)",
    "link": "https://t.me/buvshuy_oper",
    "category": "Право",
    "subs": 75156,
    "avg_views_post": 25594,
    "err": 35.0,
    "migr_sub7d": 601,
    "migr_sub30d": 2243,
    "lifetime": "4 года 17 дней"
  },
  {
    "name": "ШЕРГИНА Юрист Финансовый советник",
    "link": "https://t.me/LawAndFinance",
    "category": "Право",
    "subs": 73749,
    "avg_views_post": 21454,
    "err": 30.0,
    "migr_sub7d": -20,
    "migr_sub30d": 50,
    "lifetime": "7 лет 5 месяцев"
  },
  {
    "name": "Призыв к совести",
    "link": "https://t.me/peaceplea",
    "category": "Право",
    "subs": 70665,
    "avg_views_post": 17532,
    "err": 25.0,
    "migr_sub7d": -247,
    "migr_sub30d": -709,
    "lifetime": "3 года 2 месяца"
  },
  {
    "name": "Военные адвокаты",
    "link": "https://t.me/voen_advokaty",
    "category": "Право",
    "subs": 63732,
    "avg_views_post": 30670,
    "err": 49.0,
    "migr_sub7d": -123,
    "migr_sub30d": -313,
    "lifetime": "3 года 4 месяца"
  },
  {
    "name": "Адвокат Жорин",
    "link": "https://t.me/advokatzhorin",
    "category": "Право",
    "subs": 63413,
    "avg_views_post": 34150,
    "err": 54.0,
    "migr_sub7d": 188,
    "migr_sub30d": 911,
    "lifetime": "3 года 11 месяцев"
  },
  {
    "name": "Налоги, законы и бизнес. Марат Самитов",
    "link": "https://t.me/oooavirta",
    "category": "Право",
    "subs": 60326,
    "avg_views_post": 3849,
    "err": 7.0,
    "migr_sub7d": -42,
    "migr_sub30d": -98,
    "lifetime": "7 лет 10 месяцев"
  },
  {
    "name": "Адвокат Егоров",
    "link": "https://t.me/advocatEgorov",
    "category": "Право",
    "subs": 59968,
    "avg_views_post": 36734,
    "err": 62.0,
    "migr_sub7d": -4,
    "migr_sub30d": 442,
    "lifetime": "7 лет 6 месяцев"
  },
  {},
  {},
  {},
  {},
  {},
  {},
  {},
  {},
  {},
  {
    "name": "Закупки и тендеры по 44-ФЗ, 223-ФЗ",
    "link": "https://t.me/zakupki44fz",
    "category": "Право",
    "subs": 50096,
    "avg_views_post": 6893,
    "err": 14.0,
    "migr_sub7d": -45,
    "migr_sub30d": 469,
    "lifetime": "8 лет 3 месяца"
  },
  {
    "name": "Юридическая консультация",
    "link": "https://t.me/sovetiadvokata",
    "category": "Право",
    "subs": 49371,
    "avg_views_post": 7606,
    "err": 16.0,
    "migr_sub7d": -63,
    "migr_sub30d": 937,
    "lifetime": "5 лет 1 месяц"
  },
  {
    "name": "KALOY.RU",
    "link": "https://t.me/akaloy",
    "category": "Право",
    "subs": 49363,
    "avg_views_post": 14807,
    "err": 30.0,
    "migr_sub7d": -20,
    "migr_sub30d": 179,
    "lifetime": "7 лет 11 месяцев"
  },
  {
    "name": "Право.ru",
    "link": "https://t.me/pravo_pravo",
    "category": "Право",
    "subs": 48499,
    "avg_views_post": 10514,
    "err": 22.0,
    "migr_sub7d": 92,
    "migr_sub30d": 869,
    "lifetime": "5 лет 2 месяца"
  },
  {
    "name": "Судебная практика СКЭС ВС РФ",
    "link": "https://t.me/vs_court",
    "category": "Право",
    "subs": 48467,
    "avg_views_post": 13801,
    "err": 29.0,
    "migr_sub7d": 59,
    "migr_sub30d": 563,
    "lifetime": "6 лет 6 месяцев"
  },
  {
    "name": "ПОЛИЦИЯ 2.0",
    "link": "https://t.me/POLICE_2020",
    "category": "Право",
    "subs": 46641,
    "avg_views_post": 35339,
    "err": 76.0,
    "migr_sub7d": 315,
    "migr_sub30d": 1301,
    "lifetime": "6 лет 3 месяца"
  },
  {
    "name": "СУДЕБНАЯ ПРАКТИКА",
    "link": "https://t.me/sudpraktik",
    "category": "Право",
    "subs": 46176,
    "avg_views_post": 7560,
    "err": 17.0,
    "migr_sub7d": 198,
    "migr_sub30d": 131,
    "lifetime": "5 лет 3 месяца"
  },
  {
    "name": "КонсультантПлюс",
    "link": "https://t.me/consultant_plus",
    "category": "Право",
    "subs": 44883,
    "avg_views_post": 8572,
    "err": 20.0,
    "migr_sub7d": 27,
    "migr_sub30d": 259,
    "lifetime": "8 лет 5 месяцев"
  },
  {
    "name": "Кадровику",
    "link": "https://t.me/kadroviku",
    "category": "Право",
    "subs": 44806,
    "avg_views_post": 8332,
    "err": 19.0,
    "migr_sub7d": -16,
    "migr_sub30d": 585,
    "lifetime": "5 лет 3 месяца"
  },
  {
    "name": "Пособия/льготы/выплаты",
    "link": "https://t.me/kamyshova_ira",
    "category": "Право",
    "subs": 44157,
    "avg_views_post": 14338,
    "err": 33.0,
    "migr_sub7d": 11,
    "migr_sub30d": 24,
    "lifetime": "4 года 10 месяцев"
  },
  {
    "name": "Игорь Афонин Банкротство",
    "link": "https://t.me/joinchat/obdUnFCH1KczNzMy",
    "category": "Право",
    "subs": 41355,
    "avg_views_post": 4200,
    "err": 11.0,
    "migr_sub7d": -258,
    "migr_sub30d": -299,
    "lifetime": "3 года 3 месяца"
  },
  {
    "name": "ЖКХ",
    "link": "https://t.me/gkhvsem",
    "category": "Право",
    "subs": 40786,
    "avg_views_post": 8419,
    "err": 21.0,
    "migr_sub7d": -29,
    "migr_sub30d": -16,
    "lifetime": "7 лет 8 месяцев"
  },
  {
    "name": "ГИБДД | Новости и Законы",
    "link": "https://t.me/gibgg_russia_news",
    "category": "Право",
    "subs": 40027,
    "avg_views_post": 15251,
    "err": 39.0,
    "migr_sub7d": -179,
    "migr_sub30d": -1057,
    "lifetime": "1 год 5 месяцев"
  },
  {
    "name": "Гордон Екатерина",
    "link": "https://t.me/Gordonekaterina",
    "category": "Право",
    "subs": 39309,
    "avg_views_post": 16983,
    "err": 44.0,
    "migr_sub7d": -67,
    "migr_sub30d": -168,
    "lifetime": "2 года 8 месяцев"
  },
  {
    "name": "Соц-юрист",
    "link": "https://t.me/joinchat/_I7ih0smsgoyNDMy",
    "category": "Право",
    "subs": 38792,
    "avg_views_post": 5677,
    "err": 15.0,
    "migr_sub7d": -246,
    "migr_sub30d": -999,
    "lifetime": "1 год 3 месяца"
  },
  {
    "name": "Бывший прокурор",
    "link": "https://t.me/anon_prok",
    "category": "Право",
    "subs": 38787,
    "avg_views_post": 15073,
    "err": 39.0,
    "migr_sub7d": 40,
    "migr_sub30d": 211,
    "lifetime": "6 лет 10 месяцев"
  },
  {
    "name": "Юрист объясняет l Евгений Фурин",
    "link": "https://t.me/furinlaw",
    "category": "Право",
    "subs": 38667,
    "avg_views_post": 9108,
    "err": 24.0,
    "migr_sub7d": 478,
    "migr_sub30d": 1573,
    "lifetime": "5 лет 8 дней"
  },
  {
    "name": "ЮРИСТ В ТАТУХАХ",
    "link": "https://t.me/lawandtattoo1",
    "category": "Право",
    "subs": 38300,
    "avg_views_post": 6610,
    "err": 18.0,
    "migr_sub7d": -148,
    "migr_sub30d": -542,
    "lifetime": "5 лет 28 дней"
  },
  {
    "name": "Прокуратура Чеченской Республики",
    "link": "https://t.me/chechproc",
    "category": "Право",
    "subs": 36333,
    "avg_views_post": 4410,
    "err": 13.0,
    "migr_sub7d": 140,
    "migr_sub30d": -1450,
    "lifetime": "7 лет 3 месяца"
  },
  {
    "name": "Школа призывника | правозащитная организация",
    "link": "https://t.me/netprizyvu",
    "category": "Право",
    "subs": 36110,
    "avg_views_post": 10315,
    "err": 29.0,
    "migr_sub7d": -4,
    "migr_sub30d": 201,
    "lifetime": "5 лет 3 месяца"
  },
  {
    "name": "Avtozak LIVE",
    "link": "https://t.me/avtozaklive",
    "category": "Право",
    "subs": 35001,
    "avg_views_post": 2962,
    "err": 9.0,
    "migr_sub7d": -112,
    "migr_sub30d": -523,
    "lifetime": "6 лет 4 дня"
  },
  {
    "name": "Омбудсмен полиции",
    "link": "https://t.me/ombudsment",
    "category": "Право",
    "subs": 34104,
    "avg_views_post": 18563,
    "err": 55.0,
    "migr_sub7d": -20,
    "migr_sub30d": -249,
    "lifetime": "7 лет 8 месяцев"
  },
  {
    "name": "Елена Саакова",
    "link": "https://t.me/joinchat/TvWMgekEOzczYjcy",
    "category": "Право",
    "subs": 33789,
    "avg_views_post": 7821,
    "err": 24.0,
    "migr_sub7d": -157,
    "migr_sub30d": -992,
    "lifetime": "4 года 10 месяцев"
  },
  {
    "name": "Юристы31/Online",
    "link": "https://t.me/yurist_group31",
    "category": "Право",
    "subs": 33789,
    "avg_views_post": 6991,
    "err": 21.0,
    "migr_sub7d": 30,
    "migr_sub30d": 111,
    "lifetime": "3 года 3 месяца"
  },
  {
    "name": "Сетевые Свободы",
    "link": "https://t.me/NetFreedomsProject",
    "category": "Право",
    "subs": 33782,
    "avg_views_post": 15235,
    "err": 46.0,
    "migr_sub7d": -71,
    "migr_sub30d": -301,
    "lifetime": "5 лет 9 месяцев"
  },
  {
    "name": "Судебная практика СКГД ВС РФ",
    "link": "https://t.me/civilcourt",
    "category": "Право",
    "subs": 33555,
    "avg_views_post": 13425,
    "err": 40.0,
    "migr_sub7d": 112,
    "migr_sub30d": 262,
    "lifetime": "5 лет 3 месяца"
  },
  {
    "name": "Агент свободы | тайный юрист",
    "link": "https://t.me/agent_svobodi",
    "category": "Право",
    "subs": 33163,
    "avg_views_post": 4392,
    "err": 14.0,
    "migr_sub7d": -38,
    "migr_sub30d": -173,
    "lifetime": "4 года 5 месяцев"
  },
  {
    "name": "Земельный вопрос",
    "link": "https://t.me/zemelniyvopros",
    "category": "Право",
    "subs": 32741,
    "avg_views_post": 4125,
    "err": 13.0,
    "migr_sub7d": 352,
    "migr_sub30d": 1483,
    "lifetime": "4 года 8 месяцев"
  },
  {
    "name": "Адвокат Шупиков | 115-ФЗ",
    "link": "https://t.me/jurist",
    "category": "Право",
    "subs": 32621,
    "avg_views_post": 5897,
    "err": 19.0,
    "migr_sub7d": -35,
    "migr_sub30d": -123,
    "lifetime": "7 лет 7 месяцев"
  },
  {
    "name": "Bezdelka",
    "link": "https://t.me/bezdelkaBuh",
    "category": "Право",
    "subs": 32511,
    "avg_views_post": 3925,
    "err": 13.0,
    "migr_sub7d": 218,
    "migr_sub30d": 683,
    "lifetime": "5 лет 4 месяца"
  },
  {
    "name": "Мои Документы Москва",
    "link": "https://t.me/MDMOS",
    "category": "Право",
    "subs": 31860,
    "avg_views_post": 7238,
    "err": 23.0,
    "migr_sub7d": 79,
    "migr_sub30d": 1553,
    "lifetime": "8 лет 2 месяца"
  },
  {
    "name": "ПРОКУРАТУРА МОСКВЫ",
    "link": "https://t.me/moscowproc",
    "category": "Право",
    "subs": 31717,
    "avg_views_post": 12997,
    "err": 41.0,
    "migr_sub7d": 16,
    "migr_sub30d": 47,
    "lifetime": "4 года 2 месяца"
  },
  {
    "name": "ОВД-Инфо LIVE",
    "link": "https://t.me/ovdinfolive",
    "category": "Право",
    "subs": 31716,
    "avg_views_post": 1970,
    "err": 7.0,
    "migr_sub7d": -54,
    "migr_sub30d": -251,
    "lifetime": "3 года 9 месяцев"
  },
  {
    "name": "«ПВС» г. СПб и ЛО - Новости миграции",
    "link": "https://t.me/spbpvsmvd",
    "category": "Право",
    "subs": 31289,
    "avg_views_post": 32320,
    "err": 104.0,
    "migr_sub7d": 128,
    "migr_sub30d": 453,
    "lifetime": "3 года 22 дня"
  },
  {
    "name": "Юстиграм",
    "link": "https://t.me/yustigram",
    "category": "Право",
    "subs": 30653,
    "avg_views_post": 10900,
    "err": 36.0,
    "migr_sub7d": 3,
    "migr_sub30d": 62,
    "lifetime": "7 лет 8 месяцев"
  },
  {
    "name": "Говорит Нотарь",
    "link": "https://t.me/notariat",
    "category": "Право",
    "subs": 30421,
    "avg_views_post": 8933,
    "err": 30.0,
    "migr_sub7d": -18,
    "migr_sub30d": -6,
    "lifetime": "6 лет 1 месяц"
  },
  {
    "name": "Советы нотариуса",
    "link": "https://t.me/n_advices",
    "category": "Право",
    "subs": 30393,
    "avg_views_post": 6509,
    "err": 22.0,
    "migr_sub7d": 497,
    "migr_sub30d": 940,
    "lifetime": "5 лет 14 дней"
  },
  {
    "name": "Private Law Library | PLL Право",
    "link": "https://t.me/privlawlib",
    "category": "Право",
    "subs": 30037,
    "avg_views_post": 4769,
    "err": 16.0,
    "migr_sub7d": 14,
    "migr_sub30d": 117,
    "lifetime": "8 лет 27 дней"
  },
  {
    "name": "Суды общей юрисдикции города Москвы",
    "link": "https://t.me/moscowcourts",
    "category": "Право",
    "subs": 29534,
    "avg_views_post": 17195,
    "err": 59.0,
    "migr_sub7d": 52,
    "migr_sub30d": 306,
    "lifetime": "4 года 5 месяцев"
  },
  {
    "name": "Дмитрий Мирончук | Закон и право",
    "link": "https://t.me/ruslaw",
    "category": "Право",
    "subs": 27622,
    "avg_views_post": 3128,
    "err": 12.0,
    "migr_sub7d": -44,
    "migr_sub30d": -207,
    "lifetime": "9 лет 6 месяцев"
  },
  {
    "name": "Юрист Дмитрий Ярошенко",
    "link": "https://t.me/Juristadvokat",
    "category": "Право",
    "subs": 27602,
    "avg_views_post": 7168,
    "err": 26.0,
    "migr_sub7d": -16,
    "migr_sub30d": 51,
    "lifetime": "8 лет 11 дней"
  },
  {
    "name": "Справочник офицера",
    "link": "https://t.me/joinchat/DEi9K2EOWTJlZjgy",
    "category": "Право",
    "subs": 27359,
    "avg_views_post": 7059,
    "err": 26.0,
    "migr_sub7d": 182,
    "migr_sub30d": 868,
    "lifetime": "3 года 1 месяц"
  },
  {
    "name": "Военный советник",
    "link": "https://t.me/voen_info",
    "category": "Право",
    "subs": 27282,
    "avg_views_post": 23903,
    "err": 88.0,
    "migr_sub7d": 54,
    "migr_sub30d": 652,
    "lifetime": "3 года 3 месяца"
  },
  {
    "name": "Недвижимость и закон",
    "link": "https://t.me/pravonadom1",
    "category": "Право",
    "subs": 27140,
    "avg_views_post": 5372,
    "err": 20.0,
    "migr_sub7d": -86,
    "migr_sub30d": 246,
    "lifetime": "6 лет 19 дней"
  },
  {
    "name": "Конституционный Суд",
    "link": "https://t.me/ksrf_ru",
    "category": "Право",
    "subs": 26890,
    "avg_views_post": 4822,
    "err": 18.0,
    "migr_sub7d": -30,
    "migr_sub30d": 527,
    "lifetime": "4 года 10 месяцев"
  },
  {
    "name": "Зайдите в кадры!",
    "link": "https://t.me/kadrovoedelojournal",
    "category": "Право",
    "subs": 26740,
    "avg_views_post": 4985,
    "err": 19.0,
    "migr_sub7d": 58,
    "migr_sub30d": 372,
    "lifetime": "3 года 2 месяца"
  },
  {
    "name": "МВД по Республике Дагестан",
    "link": "https://t.me/mvd_dagestan",
    "category": "Право",
    "subs": 26061,
    "avg_views_post": 10264,
    "err": 40.0,
    "migr_sub7d": -63,
    "migr_sub30d": -180,
    "lifetime": "2 года 6 дней"
  },
  {
    "name": "Права и законы",
    "link": "https://t.me/joinchat/33DfBfhmcnYwYmQy",
    "category": "Право",
    "subs": 25236,
    "avg_views_post": 4571,
    "err": 19.0,
    "migr_sub7d": -89,
    "migr_sub30d": -403,
    "lifetime": "2 года 9 месяцев"
  },
  {
    "name": "Строптивый адвокат",
    "link": "https://t.me/vitalii_burkin",
    "category": "Право",
    "subs": 24915,
    "avg_views_post": 3143,
    "err": 13.0,
    "migr_sub7d": -92,
    "migr_sub30d": -338,
    "lifetime": "5 лет 2 месяца"
  },
  {
    "name": "ТЗС (Правозащитное Сообщество Торжества Здравого Смысла)",
    "link": "https://t.me/victoria_de_communi_sensu",
    "category": "Право",
    "subs": 24787,
    "avg_views_post": 8444,
    "err": 35.0,
    "migr_sub7d": 8,
    "migr_sub30d": 49,
    "lifetime": "4 года 5 месяцев"
  },
  {
    "name": "Юрист для врача Ангелина Романовская",
    "link": "https://t.me/mfcexpert_news",
    "category": "Право",
    "subs": 24788,
    "avg_views_post": 7369,
    "err": 30.0,
    "migr_sub7d": 103,
    "migr_sub30d": 992,
    "lifetime": "4 года 4 месяца"
  },
  {
    "name": "Клышин Алексей юрист по недвижимости",
    "link": "https://t.me/klyshin_A",
    "category": "Право",
    "subs": 24606,
    "avg_views_post": 6680,
    "err": 28.0,
    "migr_sub7d": 36,
    "migr_sub30d": 286,
    "lifetime": "3 года 3 месяца"
  },
  {
    "name": "Народный Юрист",
    "link": "https://t.me/PeopleIsLawyer",
    "category": "Право",
    "subs": 24572,
    "avg_views_post": 2911,
    "err": 12.0,
    "migr_sub7d": -111,
    "migr_sub30d": 230,
    "lifetime": "3 года 1 месяц"
  },
  {
    "name": "Судебная практика по банкротству",
    "link": "https://t.me/sudpraktik_bankrot_demo",
    "category": "Право",
    "subs": 24443,
    "avg_views_post": 3472,
    "err": 15.0,
    "migr_sub7d": 146,
    "migr_sub30d": 488,
    "lifetime": "5 лет 1 месяц"
  },
  {
    "name": "Библиотека юриста",
    "link": "https://t.me/library_lawyer",
    "category": "Право",
    "subs": 24350,
    "avg_views_post": 4348,
    "err": 18.0,
    "migr_sub7d": 14,
    "migr_sub30d": 173,
    "lifetime": "7 лет 5 месяцев"
  },
  {
    "name": "Омбудсмен Москалькова Татьяна",
    "link": "https://t.me/ombudsmanrf",
    "category": "Право",
    "subs": 24184,
    "avg_views_post": 75311,
    "err": 312.0,
    "migr_sub7d": -59,
    "migr_sub30d": 519,
    "lifetime": "3 года 3 месяца"
  },
  {
    "name": "Полезное для Кадровика",
    "link": "https://t.me/trud_krut",
    "category": "Право",
    "subs": 23860,
    "avg_views_post": 2236,
    "err": 10.0,
    "migr_sub7d": -38,
    "migr_sub30d": 422,
    "lifetime": "4 года 4 дня"
  },
  {
    "name": "Объединённая пресс-служба судов Санкт-Петербурга",
    "link": "https://t.me/SPbGS",
    "category": "Право",
    "subs": 23822,
    "avg_views_post": 4090,
    "err": 18.0,
    "migr_sub7d": 52,
    "migr_sub30d": 340,
    "lifetime": "8 лет 11 месяцев"
  },
  {
    "name": "Клуб правообладателей",
    "link": "https://t.me/bchlaw",
    "category": "Право",
    "subs": 23661,
    "avg_views_post": 8548,
    "err": 37.0,
    "migr_sub7d": 238,
    "migr_sub30d": 614,
    "lifetime": "5 лет 10 месяцев"
  },
  {
    "name": "ТРУДОВЫЕ СПОРЫ",
    "link": "https://t.me/sudpraktik_trud",
    "category": "Право",
    "subs": 23382,
    "avg_views_post": 4871,
    "err": 21.0,
    "migr_sub7d": 180,
    "migr_sub30d": 646,
    "lifetime": "3 года 9 месяцев"
  },
  {
    "name": "Охрана труда",
    "link": "https://t.me/ohranatruda_official",
    "category": "Право",
    "subs": 23276,
    "avg_views_post": 6140,
    "err": 27.0,
    "migr_sub7d": 1,
    "migr_sub30d": 30,
    "lifetime": "3 года 3 месяца"
  },
  {
    "name": "Кирилл Гавриличев",
    "link": "https://t.me/gavrilichevkirill",
    "category": "Право",
    "subs": 23140,
    "avg_views_post": 13037,
    "err": 57.0,
    "migr_sub7d": -57,
    "migr_sub30d": 949,
    "lifetime": "2 года 2 месяца"
  },
  {
    "name": "Законодатель",
    "link": "https://t.me/zaconodatel",
    "category": "Право",
    "subs": 23046,
    "avg_views_post": 2895,
    "err": 13.0,
    "migr_sub7d": -55,
    "migr_sub30d": 254,
    "lifetime": "6 лет 6 месяцев"
  },
  {
    "name": "Земельное право",
    "link": "https://t.me/zemelnoe_pravo",
    "category": "Право",
    "subs": 22907,
    "avg_views_post": 7737,
    "err": 34.0,
    "migr_sub7d": 70,
    "migr_sub30d": 291,
    "lifetime": "4 года 16 дней"
  },
  {
    "name": "Корпоративные споры • Case by Case",
    "link": "https://t.me/corplawpro",
    "category": "Право",
    "subs": 22902,
    "avg_views_post": 2104,
    "err": 10.0,
    "migr_sub7d": 195,
    "migr_sub30d": 136,
    "lifetime": "8 лет 11 месяцев"
  },
  {
    "name": "ЮРИСПРУДЕНЦИЯ",
    "link": "https://t.me/yrisprudencia",
    "category": "Право",
    "subs": 22083,
    "avg_views_post": 3441,
    "err": 16.0,
    "migr_sub7d": 173,
    "migr_sub30d": 604,
    "lifetime": "3 года 7 месяцев"
  },
  {
    "name": "ГАРАНТ. Новости законодательства",
    "link": "https://t.me/garantnews",
    "category": "Право",
    "subs": 21858,
    "avg_views_post": 3323,
    "err": 16.0,
    "migr_sub7d": 56,
    "migr_sub30d": 322,
    "lifetime": "9 лет 4 месяца"
  },
  {
    "name": "Право: горячая линия",
    "link": "https://t.me/svohotline",
    "category": "Право",
    "subs": 21803,
    "avg_views_post": 21359,
    "err": 98.0,
    "migr_sub7d": 100,
    "migr_sub30d": 622,
    "lifetime": "1 год 1 месяц"
  },
  {
    "name": "ГИБДД | Последние Новости и Законы",
    "link": "https://t.me/gibdd_russia_smi",
    "category": "Право",
    "subs": 21629,
    "avg_views_post": 4396,
    "err": 21.0,
    "migr_sub7d": -126,
    "migr_sub30d": -603,
    "lifetime": "1 год 8 месяцев"
  }
]